odoo/addons/account_account_constraint_code/README.rst
odoo/addons/account_account_constraint_code/__init__.py
odoo/addons/account_account_constraint_code/__manifest__.py
odoo/addons/account_account_constraint_code/i18n/account_account_constraint_code.pot
odoo/addons/account_account_constraint_code/i18n/es.po
odoo/addons/account_account_constraint_code/i18n/fr.po
odoo/addons/account_account_constraint_code/i18n/it.po
odoo/addons/account_account_constraint_code/models/__init__.py
odoo/addons/account_account_constraint_code/models/account_account.py
odoo/addons/account_account_constraint_code/readme/CONFIGURE.rst
odoo/addons/account_account_constraint_code/readme/CONTRIBUTORS.rst
odoo/addons/account_account_constraint_code/readme/DESCRIPTION.rst
odoo/addons/account_account_constraint_code/static/description/icon.png
odoo/addons/account_account_constraint_code/static/description/index.html
odoo/addons/account_account_constraint_code/tests/__init__.py
odoo/addons/account_account_constraint_code/tests/test_account_account.py
odoo14_addon_account_account_constraint_code-14.0.1.0.1.dev12.dist-info/METADATA
odoo14_addon_account_account_constraint_code-14.0.1.0.1.dev12.dist-info/WHEEL
odoo14_addon_account_account_constraint_code-14.0.1.0.1.dev12.dist-info/top_level.txt
odoo14_addon_account_account_constraint_code-14.0.1.0.1.dev12.dist-info/RECORD
